agentlego/__init__.py
agentlego/schema.py
agentlego/search.py
agentlego/types.py
agentlego/version.py
agentlego/apis/__init__.py
agentlego/apis/tool.py
agentlego/parsers/__init__.py
agentlego/parsers/base_parser.py
agentlego/parsers/custom_parsers.py
agentlego/parsers/default_parser.py
agentlego/parsers/naive_parser.py
agentlego/server/__init__.py
agentlego/server/__main__.py
agentlego/server/server.py
agentlego/testing/__init__.py
agentlego/testing/setup_tool.py
agentlego/tools/__init__.py
agentlego/tools/base.py
agentlego/tools/func.py
agentlego/tools/remote.py
agentlego/tools/calculator/__init__.py
agentlego/tools/calculator/python_calculator.py
agentlego/tools/image_canny/__init__.py
agentlego/tools/image_canny/canny_to_image.py
agentlego/tools/image_canny/image_to_canny.py
agentlego/tools/image_depth/__init__.py
agentlego/tools/image_depth/depth_to_image.py
agentlego/tools/image_depth/image_to_depth.py
agentlego/tools/image_editing/__init__.py
agentlego/tools/image_editing/expansion.py
agentlego/tools/image_editing/remove.py
agentlego/tools/image_editing/replace.py
agentlego/tools/image_editing/stylization.py
agentlego/tools/image_pose/__init__.py
agentlego/tools/image_pose/facelandmark.py
agentlego/tools/image_pose/image_to_pose.py
agentlego/tools/image_pose/pose_to_image.py
agentlego/tools/image_scribble/__init__.py
agentlego/tools/image_scribble/image_to_scribble.py
agentlego/tools/image_scribble/scribble_to_image.py
agentlego/tools/image_text/__init__.py
agentlego/tools/image_text/image_to_text.py
agentlego/tools/image_text/text_to_image.py
agentlego/tools/imagebind/__init__.py
agentlego/tools/imagebind/anything_to_image.py
agentlego/tools/imagebind/data.py
agentlego/tools/imagebind/models/__init__.py
agentlego/tools/imagebind/models/helpers.py
agentlego/tools/imagebind/models/imagebind_model.py
agentlego/tools/imagebind/models/multimodal_preprocessors.py
agentlego/tools/imagebind/models/transformer.py
agentlego/tools/object_detection/__init__.py
agentlego-0.2.0.dist-info/LICENSE
agentlego-0.2.0.dist-info/METADATA
agentlego-0.2.0.dist-info/WHEEL
agentlego-0.2.0.dist-info/entry_points.txt
agentlego-0.2.0.dist-info/top_level.txt
agentlego-0.2.0.dist-info/RECORD
