Metadata-Version: 2.1
Name: agentlego
Version: 0.2.0
Summary: AgentLego is a versatile tool library for enhancing LLM-based agents.
Author: AgentLego Contributors
Maintainer-email: mzr1996 <mzr1996@163.com>
License: Apache License 2.0
Project-URL: Documentation, https://agentlego.readthedocs.io
Project-URL: Repository, https://github.com/InternLM/agentlego
Keywords: LLM,Multi-Modality,AI Agent
Classifier: Topic :: Scientific/Engineering :: Artificial Intelligence
Classifier: Programming Language :: Python :: 3
Requires-Python: >=3.8
License-File: LICENSE
Requires-Dist: addict
Requires-Dist: func-timeout
Requires-Dist: numpy
Requires-Dist: openapi-pydantic
Requires-Dist: packaging
Requires-Dist: Pillow
Requires-Dist: prompt-toolkit
Requires-Dist: pydantic >=2.0
Requires-Dist: pyyaml
Requires-Dist: requests
Requires-Dist: rich
Requires-Dist: thefuzz
Requires-Dist: tqdm
Requires-Dist: typing-extensions
Provides-Extra: all
Requires-Dist: fastapi ; extra == 'all'
Requires-Dist: openai ; extra == 'all'
Requires-Dist: python-multipart ; extra == 'all'
Requires-Dist: sentence-transformers ; extra == 'all'
Requires-Dist: torch ; extra == 'all'
Requires-Dist: torchaudio ; extra == 'all'
Requires-Dist: torchvision ; extra == 'all'
Requires-Dist: typing-extensions ; extra == 'all'
Requires-Dist: uvicorn[standard] ; extra == 'all'
Requires-Dist: easyocr ; extra == 'all'
Provides-Extra: server
Requires-Dist: fastapi ; extra == 'server'
Requires-Dist: makefun ; extra == 'server'
Requires-Dist: python-multipart ; extra == 'server'
Requires-Dist: typer >=0.9 ; extra == 'server'
Requires-Dist: uvicorn[standard] ; extra == 'server'
